evmrpcproxy/__init__.py
evmrpcproxy/__main__.py
evmrpcproxy/api_app.py
evmrpcproxy/api_handlers.py
evmrpcproxy/blockchains.json
evmrpcproxy/blockchains.py
evmrpcproxy/common.py
evmrpcproxy/runlib.py
evmrpcproxy/settings.py
evmrpcproxy/tasks.py
evmrpcproxy/evmrpc/__init__.py
evmrpcproxy/evmrpc/evmrpc_check.py
evmrpcproxy/evmrpc/evmrpc_client.py
evmrpcproxy/evmrpc/evmrpc_config.py
evmrpcproxy/evmrpc/evmrpc_config.yaml
evmrpcproxy/evmrpc/evmrpc_config_model.py
evmrpcproxy/evmrpc/evmrpc_errors.py
evmrpcproxy/evmrpc/evmrpc_gas.py
evmrpcproxy/evmrpc/evmrpc_middleware.py
evmrpcproxy/evmrpc/evmrpc_models.py
evmrpcproxy/evmrpc/evmrpc_utils.py
evmrpcproxy/evmrpc/utils.py
evmrpcproxy-0.2.0.dist-info/METADATA
evmrpcproxy-0.2.0.dist-info/WHEEL
evmrpcproxy-0.2.0.dist-info/entry_points.txt
evmrpcproxy-0.2.0.dist-info/RECORD
