Metadata-Version: 2.4
Name: evmrpcproxy
Version: 0.2.0
Author-email: HoverHell <hoverhell@gmail.com>
Requires-Python: ~=3.11
Requires-Dist: hyapp<6,>=5
Requires-Dist: orjson<4,>=3.10.15
Requires-Dist: sentry-sdk[fastapi]<3,>=2.22.0
Requires-Dist: typer<0.13,>=0.12.5
Requires-Dist: uvicorn<0.31,>=0.30.6
